{
    "_approved": true,
    "manufacturer": "Philio Technology Corp",
    "manufacturerId": "0x013c",
    "label": "PAN08",
    "description": "PAN08-1 In Wall Roller Shutter Controller",
    "devices": [
        {
            "productType": "0x0001",
            "productId": "0x0015"
        },
        {
            "productType": "0x0001",
            "productId": "0x0006"
        }
    ],
    "firmwareVersion": {
        "min": "0.0",
        "max": "255.255"
    },
    "associations": {
        "1": {
            "label": "Lifeline",
            "maxNodes": 1,
            "isLifeline": true
        }
    },
    "paramInformation": {
        "1": {
            "label": "Watt meter report period",
            "description": "Watt Meter Report Period. Unit: 5 seconds.",
            "valueSize": 2,
            "minValue": 1,
            "maxValue": 32767,
            "defaultValue": 720,
            "readOnly": false,
            "writeOnly": false,
            "allowManualEntry": true
        },
        "2": {
            "label": "kWh meter report period",
            "description": "kWH Meter Report Period. Unit: 10 minutes.",
            "valueSize": 2,
            "minValue": 1,
            "maxValue": 32767,
            "defaultValue": 6,
            "readOnly": false,
            "writeOnly": false,
            "allowManualEntry": true
        },
        "3": {
            "label": "Threshold of Watt for Load Caution",
            "description": "Threshold of Watt for Load Caution. Unit: 1 watt",
            "valueSize": 2,
            "minValue": 10,
            "maxValue": 1100,
            "defaultValue": 1100,
            "readOnly": false,
            "writeOnly": false,
            "allowManualEntry": true
        },
        "4": {
            "label": "Threshold of kWh for Load Caution",
            "valueSize": 2,
            "minValue": 1,
            "maxValue": 10000,
            "defaultValue": 10000,
            "readOnly": false,
            "writeOnly": false,
            "allowManualEntry": true,
            "description": "Threshold of kWH for Load Caution. Unit: 1 kWH"
        },
        "5": {
            "label": "External switch type",
            "description": "External switch type: 1-> One Push button, 2->Two Push button",
            "valueSize": 1,
            "minValue": 1,
            "maxValue": 2,
            "readOnly": false,
            "writeOnly": false,
            "allowManualEntry": true,
            "defaultValue": 1
        },
        "6": {
            "label": "Level report mode",
            "description": "Level report mode: 1-> Report destination level in 5s, 2-> Report 10 percent level while running",
            "valueSize": 1,
            "minValue": 1,
            "maxValue": 2,
            "readOnly": false,
            "writeOnly": false,
            "allowManualEntry": true,
            "defaultValue": 1
        }
    }
}